[
  {
    "start": 0.0,
    "end": 0.36,
    "text": "Xin"
  },
  {
    "start": 0.36,
    "end": 0.79,
    "text": "chào"
  },
  {
    "start": 0.79,
    "end": 1.15,
    "text": "tất"
  },
  {
    "start": 1.15,
    "end": 1.44,
    "text": "cả"
  },
  {
    "start": 1.44,
    "end": 1.8,
    "text": "các"
  },
  {
    "start": 1.8,
    "end": 2.09,
    "text": "bé"
  },
  {
    "start": 2.09,
    "end": 2.45,
    "text": "yêu"
  },
  {
    "start": 2.45,
    "end": 2.88,
    "text": "quý!"
  },
  {
    "start": 2.88,
    "end": 3.17,
    "text": "Cô"
  },
  {
    "start": 3.17,
    "end": 3.46,
    "text": "là"
  },
  {
    "start": 3.46,
    "end": 3.89,
    "text": "(tên"
  },
  {
    "start": 3.89,
    "end": 4.32,
    "text": "giáo"
  },
  {
    "start": 4.32,
    "end": 4.82,
    "text": "viên)"
  },
  {
    "start": 4.82,
    "end": 5.11,
    "text": "và"
  },
  {
    "start": 5.11,
    "end": 5.47,
    "text": "hôm"
  },
  {
    "start": 5.47,
    "end": 5.9,
    "text": "nay,"
  },
  {
    "start": 5.9,
    "end": 6.4,
    "text": "chúng"
  },
  {
    "start": 6.4,
    "end": 6.83,
    "text": "mình"
  },
  {
    "start": 6.83,
    "end": 7.12,
    "text": "sẽ"
  },
  {
    "start": 7.12,
    "end": 7.55,
    "text": "cùng"
  },
  {
    "start": 7.55,
    "end": 7.98,
    "text": "nhau"
  },
  {
    "start": 7.98,
    "end": 8.34,
    "text": "bắt"
  },
  {
    "start": 8.34,
    "end": 8.7,
    "text": "đầu"
  },
  {
    "start": 8.7,
    "end": 9.06,
    "text": "một"
  },
  {
    "start": 9.06,
    "end": 9.63,
    "text": "chuyến"
  },
  {
    "start": 9.63,
    "end": 10.13,
    "text": "phiêu"
  },
  {
    "start": 10.13,
    "end": 10.49,
    "text": "lưu"
  },
  {
    "start": 10.49,
    "end": 10.92,
    "text": "thật"
  },
  {
    "start": 10.92,
    "end": 11.28,
    "text": "thú"
  },
  {
    "start": 11.28,
    "end": 11.57,
    "text": "vị"
  },
  {
    "start": 11.57,
    "end": 11.93,
    "text": "vào"
  },
  {
    "start": 11.93,
    "end": 12.29,
    "text": "một"
  },
  {
    "start": 12.29,
    "end": 12.65,
    "text": "nơi"
  },
  {
    "start": 12.65,
    "end": 13.01,
    "text": "rất"
  },
  {
    "start": 13.01,
    "end": 13.37,
    "text": "đặc"
  },
  {
    "start": 13.37,
    "end": 13.87,
    "text": "biệt:"
  },
  {
    "start": 13.87,
    "end": 14.16,
    "text": "đó"
  },
  {
    "start": 14.16,
    "end": 14.45,
    "text": "là"
  },
  {
    "start": 14.45,
    "end": 14.81,
    "text": "khu"
  },
  {
    "start": 14.81,
    "end": 15.24,
    "text": "rừng"
  },
  {
    "start": 15.24,
    "end": 15.67,
    "text": "xanh"
  },
  {
    "start": 15.67,
    "end": 16.1,
    "text": "thẳm"
  },
  {
    "start": 16.1,
    "end": 16.53,
    "text": "đấy."
  },
  {
    "start": 16.53,
    "end": 16.89,
    "text": "Các"
  },
  {
    "start": 16.89,
    "end": 17.25,
    "text": "con"
  },
  {
    "start": 17.25,
    "end": 17.54,
    "text": "có"
  },
  {
    "start": 17.54,
    "end": 17.9,
    "text": "sẵn"
  },
  {
    "start": 17.9,
    "end": 18.33,
    "text": "sàng"
  },
  {
    "start": 18.33,
    "end": 18.69,
    "text": "gặp"
  },
  {
    "start": 18.69,
    "end": 18.98,
    "text": "gỡ"
  },
  {
    "start": 18.98,
    "end": 19.48,
    "text": "những"
  },
  {
    "start": 19.48,
    "end": 19.98,
    "text": "người"
  },
  {
    "start": 19.98,
    "end": 20.34,
    "text": "bạn"
  },
  {
    "start": 20.34,
    "end": 20.77,
    "text": "động"
  },
  {
    "start": 20.77,
    "end": 21.13,
    "text": "vật"
  },
  {
    "start": 21.13,
    "end": 21.42,
    "text": "dễ"
  },
  {
    "start": 21.42,
    "end": 21.99,
    "text": "thương"
  },
  {
    "start": 21.99,
    "end": 22.49,
    "text": "không"
  },
  {
    "start": 22.49,
    "end": 22.92,
    "text": "nào?"
  }
]