[
  {
    "start": 0.0,
    "end": 0.34,
    "text": "Mầm"
  },
  {
    "start": 0.34,
    "end": 0.68,
    "text": "non"
  },
  {
    "start": 0.68,
    "end": 1.02,
    "text": "lớn"
  },
  {
    "start": 1.02,
    "end": 1.36,
    "text": "dần"
  },
  {
    "start": 1.36,
    "end": 1.7,
    "text": "thành"
  },
  {
    "start": 1.7,
    "end": 2.09,
    "text": "cây"
  },
  {
    "start": 2.09,
    "end": 2.43,
    "text": "con."
  },
  {
    "start": 2.84,
    "end": 3.18,
    "text": "Lá"
  },
  {
    "start": 3.18,
    "end": 3.52,
    "text": "xanh"
  },
  {
    "start": 3.52,
    "end": 3.94,
    "text": "giúp"
  },
  {
    "start": 3.94,
    "end": 4.32,
    "text": "cây"
  },
  {
    "start": 4.32,
    "end": 4.66,
    "text": "nhận"
  },
  {
    "start": 4.66,
    "end": 5.0,
    "text": "ánh"
  },
  {
    "start": 5.0,
    "end": 5.34,
    "text": "sáng,"
  },
  {
    "start": 5.53,
    "end": 5.87,
    "text": "còn"
  },
  {
    "start": 5.87,
    "end": 6.21,
    "text": "rễ"
  },
  {
    "start": 6.21,
    "end": 6.63,
    "text": "tiếp"
  },
  {
    "start": 6.63,
    "end": 6.97,
    "text": "tục"
  },
  {
    "start": 6.97,
    "end": 7.31,
    "text": "hút"
  },
  {
    "start": 7.31,
    "end": 7.73,
    "text": "nước"
  },
  {
    "start": 7.73,
    "end": 8.07,
    "text": "và"
  },
  {
    "start": 8.07,
    "end": 8.41,
    "text": "chất"
  },
  {
    "start": 8.41,
    "end": 8.75,
    "text": "dinh"
  },
  {
    "start": 8.75,
    "end": 9.21,
    "text": "dưỡng"
  },
  {
    "start": 9.21,
    "end": 9.55,
    "text": "trong"
  },
  {
    "start": 9.55,
    "end": 10.3,
    "text": "đất."
  }
]